scrapy_new/__init__.py
scrapy_new/new.py
scrapy_new/templates/command.py.mako
scrapy_new/templates/extension.py.mako
scrapy_new/templates/item.py.mako
scrapy_new/templates/middleware.py.mako
scrapy_new/templates/model.py.mako
scrapy_new/templates/pipeline.py.mako
scrapy_new/templates/spider.py.mako
scrapy_new/templates/spider_middleware.py.mako
scrapy_new-0.2.1.dist-info/entry_points.txt
scrapy_new-0.2.1.dist-info/LICENSE
scrapy_new-0.2.1.dist-info/WHEEL
scrapy_new-0.2.1.dist-info/METADATA
scrapy_new-0.2.1.dist-info/RECORD
